lfm_flow/__init__.py
lfm_flow/kernels/__init__.py
lfm_flow/kernels/kernels.py
lfm_flow/kernels/lfm_kernels.py
lfm_flow/latentforcemodels/__init__.py
lfm_flow/latentforcemodels/llfm.py
lfm_flow-0.0.2.dist-info/METADATA
lfm_flow-0.0.2.dist-info/WHEEL
lfm_flow-0.0.2.dist-info/top_level.txt
lfm_flow-0.0.2.dist-info/RECORD
