Metadata-Version: 2.1
Name: lfm-flow
Version: 0.0.2
Summary: LFM in TensorFlow
Home-page: https://github.com/danieljtait/lfm_flow
Author: Daniel Tait
Author-email: daniel.tait@warwick.ac.uk
License: UNKNOWN
Platform: UNKNOWN
Classifier: Programming Language :: Python :: 3
Classifier: License :: OSI Approved :: MIT License
Classifier: Operating System :: OS Independent
Requires-Dist: numpy
Requires-Dist: scipy
Requires-Dist: matplotlib (>=2.2.0)
Requires-Dist: tensorflow (>=1.13.0)
